yt/environment/__init__.py
yt/environment/configs_provider.py
yt/environment/default_config.py
yt/environment/external_component.py
yt/environment/helpers.py
yt/environment/init_cluster.py
yt/environment/init_operation_archive.py
yt/environment/init_queue_agent_state.py
yt/environment/local_cluster_configuration.py
yt/environment/local_cypress.py
yt/environment/porto_helpers.py
yt/environment/watcher.py
yt/environment/yt_env.py
yt/environment/api/__init__.py
yt/local/__init__.py
yt/local/commands.py
yt/local/helpers.py
yt/test_helpers/__init__.py
yt/test_helpers/authors.py
yt/test_helpers/cleanup.py
yt/test_helpers/filter_by_category.py
yt/test_helpers/fork_class.py
yt/test_helpers/job_events.py
yt/test_helpers/profiler.py
yt/test_helpers/set_timeouts.py
ytsaurus_local-0.1.2.post0.data/scripts/yt_env_watcher
ytsaurus_local-0.1.2.post0.data/scripts/yt_local
ytsaurus_local-0.1.2.post0.dist-info/METADATA
ytsaurus_local-0.1.2.post0.dist-info/WHEEL
ytsaurus_local-0.1.2.post0.dist-info/top_level.txt
ytsaurus_local-0.1.2.post0.dist-info/RECORD
